ftc_api/__init__.py
ftc_api/client.py
ftc_api/errors.py
ftc_api/types.py
ftc_api/api/__init__.py
ftc_api/api/alliance_selection/__init__.py
ftc_api/api/alliance_selection/get_v_2_0_season_alliances_event_code.py
ftc_api/api/alliance_selection/get_v_2_0_season_alliances_event_code_selection.py
ftc_api/api/awards/__init__.py
ftc_api/api/awards/get_v2_0_season_awards_list.py
ftc_api/api/awards/get_v_2_0_season_awards_event_code.py
ftc_api/api/awards/get_v_2_0_season_awards_event_code_team_number.py
ftc_api/api/awards/get_v_2_0_season_awards_team_number.py
ftc_api/api/general/__init__.py
ftc_api/api/general/get_v2_0.py
ftc_api/api/leagues/__init__.py
ftc_api/api/leagues/get_v2_0_season_leagues.py
ftc_api/api/leagues/get_v_2_0_season_leagues_members_region_code_league_code.py
ftc_api/api/leagues/get_v_2_0_season_leagues_rankings_region_code_league_code.py
ftc_api/api/match_results/__init__.py
ftc_api/api/match_results/get_v_2_0_season_scores_event_code_tournament_level.py
ftc_api/api/rankings/__init__.py
ftc_api/api/rankings/get_v_2_0_season_rankings_event_code.py
ftc_api/api/schedule/__init__.py
ftc_api/api/schedule/get_v_2_0_season_schedule_event_code_tournament_level_hybrid.py
ftc_api/api/season_data/__init__.py
ftc_api/api/season_data/get_v2_0_season.py
ftc_api/api/season_data/get_v2_0_season_events.py
ftc_api/api/season_data/get_v2_0_season_teams.py
ftc_api/models/__init__.py
ftc_api/models/alliance.py
ftc_api/models/alliance_selection.py
ftc_api/models/alliance_selection_details.py
ftc_api/models/api_information.py
ftc_api/models/auto_navigated_status.py
ftc_api/models/auto_navigation.py
ftc_api/models/award.py
ftc_api/models/award_assignment.py
ftc_api/models/award_assignment_list.py
ftc_api/models/award_list.py
ftc_api/models/barcode_element.py
ftc_api/models/coordinate.py
ftc_api/models/coordinate_equality_comparer.py
ftc_api/models/coordinate_sequence.py
ftc_api/models/coordinate_sequence_factory.py
ftc_api/models/dimension.py
ftc_api-0.4.0.dist-info/LICENSE
ftc_api-0.4.0.dist-info/METADATA
ftc_api-0.4.0.dist-info/WHEEL
ftc_api-0.4.0.dist-info/top_level.txt
ftc_api-0.4.0.dist-info/RECORD
