Metadata-Version: 2.1
Name: ftc-api
Version: 0.4.0
Summary: A python client to access the FIRST Tech Challenge API
Author-email: Ashwin Naren <arihant2math@gmail.com>
License: Copyright 2023 Ashwin Naren
Project-URL: Homepage, https://arihant2math.github.io/ftc-api/
Project-URL: Repository, https://github.com/arihant2math/ftc-api.git
Project-URL: Documentation, https://arihant2math.github.io/ftc-api/
Project-URL: Bug Tracker, https://github.com/arihant2math/ftc-api/issues
Keywords: ftc
Classifier: Programming Language :: Python :: 3
Classifier: Development Status :: 4 - Beta
Classifier: License :: OSI Approved :: MIT License
Requires-Python: >=3.7
License-File: LICENSE
Requires-Dist: httpx[http2]
Requires-Dist: python-dateutil
Requires-Dist: attrs
Provides-Extra: dev
Requires-Dist: black ; extra == 'dev'
Requires-Dist: sphinx ; extra == 'dev'
Requires-Dist: furo ; extra == 'dev'
